[[
  "1",
  "2",
  "3",
  "4",
  "5",
  "6",
  "7",
  "8",
  "9",
  "10",
  "11",
  "12",
  "13",
  "14",
  "15",
  "16",
  "17",
  "18",
  "19",
  "20"
],{
  "id": "21",
  "name": "22",
  "location": "23",
  "bookings": "24"
},{
  "id": "25",
  "name": "26",
  "location": "27",
  "bookings": "28"
},{
  "id": "29",
  "name": "30",
  "location": "31",
  "bookings": "32"
},{
  "id": "33",
  "bookings": "34"
},{
  "id": "35",
  "bookings": "36"
},{
  "id": "37",
  "bookings": "38"
},{
  "id": "39",
  "bookings": "40"
},{
  "id": "41",
  "name": "42",
  "location": "43",
  "bookings": "44"
},{
  "id": "45",
  "bookings": "46"
},{
  "id": "47",
  "name": "48",
  "location": "49",
  "bookings": "50"
},{
  "id": "51",
  "name": "48",
  "location": "49",
  "bookings": "52"
},{
  "id": "53",
  "name": "48",
  "location": "49",
  "bookings": "54"
},{
  "id": "55",
  "name": "48",
  "location": "49",
  "bookings": "56"
},{
  "id": "57",
  "name": "48",
  "location": "49",
  "bookings": "58"
},{
  "id": "59",
  "name": "48",
  "location": "49",
  "bookings": "60"
},{
  "id": "61",
  "name": "48",
  "location": "49",
  "bookings": "62"
},{
  "id": "63",
  "name": "48",
  "location": "49",
  "bookings": "64"
},{
  "id": "65",
  "name": "48",
  "location": "49",
  "bookings": "66"
},{
  "id": "67",
  "name": "48",
  "location": "49",
  "bookings": "68"
},{
  "id": "69",
  "name": "48",
  "location": "49",
  "bookings": "70"
},"01ed8529-ad31-4351-b092-21cabb931e16","Armagan","Kreuzberg",[
  "71",
  "72",
  "73",
  "74"
],"68e6a08c-f4cf-486e-b1df-dac92576bc48","Mert","Mitte",[
  "75"
],"db80ba9d-c327-4222-b62c-f5f230a3e0b6","Betul","Tegel",[
  "76",
  "77",
  "78"
],"92f71ad7-a806-41f6-bd33-59fcc754162f",[],"269e3f80-42bf-4409-af1e-b897dedfde4c",[],"59be8bc5-f28a-48e3-a98b-a7a7d40c4dfd",[],"7fa6f1dc-76b5-450b-8aba-f73ea0104bd9",[],"66f47f82-063c-43d7-9c6e-5311f9d31fa2","new passenger","Moda",[],"b8ca32d3-f610-4e41-8534-b53afb5c01fd",[],"ede41daa-a3d4-427f-96aa-94dda0c0299a","weird client","kuzguncuk",[],"88b04838-742d-4aa2-9e9f-b06a363d454c",[],"c2c00469-2022-4f27-b3e9-5705535c2a42",[],"1d569e2b-d8a3-410f-a957-85e55896ca11",[],"437f691b-a097-4daf-ba56-ffff33bc2935",[],"91effbd5-e751-4403-8bd6-aec6fe335806",[],"05a1e9a3-da4a-46a3-8086-65933d7cc1e3",[],"d50628c1-6922-43ef-beeb-df9073211b5a",[],"55c0329f-60c3-4810-9388-a26f096a6449",[],"e36afcbc-8349-43a4-b8e8-445ab464050a",[],"5d5c3d85-b328-457e-8598-4d0fe69c252c",[],{
  "driver": "79",
  "passenger": "80",
  "origin": "23",
  "destination": "81"
},{
  "driver": "79",
  "passenger": "80",
  "origin": "81",
  "destination": "27"
},{
  "driver": "79",
  "passenger": "80",
  "origin": "27",
  "destination": "23"
},{
  "driver": "79",
  "passenger": "80",
  "origin": "23",
  "destination": "82"
},{
  "driver": "79",
  "passenger": "83",
  "origin": "27",
  "destination": "23"
},{
  "driver": "84",
  "passenger": "85",
  "origin": "82",
  "destination": "23"
},{
  "driver": "86",
  "passenger": "87",
  "origin": "23",
  "destination": "88"
},{
  "driver": "89",
  "passenger": "90",
  "origin": "88",
  "destination": "27"
},{
  "id": "91",
  "name": "92",
  "location": "93"
},{
  "id": "21",
  "name": "22",
  "location": "23",
  "bookings": "24"
},"Neukolln","SXF",{
  "id": "25",
  "name": "26",
  "location": "27",
  "bookings": "28"
},{
  "id": "91",
  "name": "92",
  "location": "93"
},{
  "id": "29",
  "name": "30",
  "location": "31",
  "bookings": "32"
},{
  "id": "91",
  "name": "92",
  "location": "93"
},{
  "id": "29",
  "name": "30",
  "location": "31",
  "bookings": "32"
},"TXL",{
  "id": "91",
  "name": "92",
  "location": "93"
},{
  "id": "29",
  "name": "30",
  "location": "31",
  "bookings": "32"
},"33722c67-7b62-4dbb-81cb-e64a9aba6713","Stefan","Treptower Park"]